{
      "nodes": [
            {
                  "data": {
                        "id": "101",
                        "label": "Convergence",
                        "meta": " RA02 ",
                        "content": "Convergent sequences have a well-defined limit.",
                        "notes": "101-snippet.html",
                        "video": "",
                        "webwork": "https://jupyterhub.mat.tu-harburg.de/webwork2/html2xml?&answersSubmitted=0&sourceFilePath=Library/WHFreeman/Rogawski_Calculus_Early_Transcendentals_Second_Edition/10_Infinite_Series/10.1_Sequences/10.1.31.pg&problemSeed=123567890&displayMode=MathJax&courseID=pontifex&userID=pontifexuser&course_password=ki(JH7j3m4)k_46)&outputformat=simple",
                        "podcast": "",
                        "youtube": "https://youtu.be/1SguKALJji8?start=367",
                        "spotify": ""
                  }
            },
            {
                  "data": {
                        "id": "102",
                        "label": "Bounded\nSequences",
                        "meta": " RA03 ",
                        "content": "Sequences can be bounded from above and from below. The values of a bounded sequence cannot become arbitrarily large.",
                        "notes": "102-snippet.html",
                        "video": "",
                        "webwork": "https://jupyterhub.mat.tu-harburg.de/webwork2/html2xml?&answersSubmitted=0&sourceFilePath=Library/WinonaState/StewartCalcEarlyTran7ed/Chap11Section01/SCalcET7-11-1-037.pg&problemSeed=123567890&displayMode=MathJax&courseID=pontifex&userID=pontifexuser&course_password=ki(JH7j3m4)k_46)&outputformat=simple",
                        "podcast": "",
                        "youtube": "https://youtu.be/k-Wm6gJYfrw?start=221",
                        "spotify": "",
                        "color": "#b8b8b8"
                  }
            },
            {
                  "data": {
                        "id": "109",
                        "label": "Limit Inferior and\nLimit Superior",
                        "meta": "RA11+RA12 ",
                        "content": "The largest and smallest limit of all convergent subsequences.",
                        "notes": "109-snippet.html",
                        "video": "",
                        "exercise": "ratest11.html",
                        "podcast": "",
                        "youtube": "https://youtu.be/-y0v2V0-_8E?start=21",
                        "spotify": "",
                        "color": "#b8b8b8"
                  }
            },
            {
                  "data": {
                        "id": "103",
                        "label": "Limit Theorems",
                        "meta": " RA04 ",
                        "content": "Combining limits is a useful tool to deduce convergence and the limit of a more complicated sequence from the convergence of simpler building blocks.",
                        "notes": "103-snippet.html",
                        "video": "",
                        "webwork": "https://jupyterhub.mat.tu-harburg.de/webwork2/html2xml?&answersSubmitted=0&sourceFilePath=Library/Dartmouth/setStewartCh12S1/problem_7.pg&problemSeed=123567890&displayMode=MathJax&courseID=pontifex&userID=pontifexuser&course_password=ki(JH7j3m4)k_46)&outputformat=simple",
                        "podcast": "",
                        "youtube": "https://youtu.be/237VMLNVtQs?start=18",
                        "spotify": "",
                        "color": "#b8b8b8"
                  }
            },
            {
                  "data": {
                        "id": "104",
                        "label": "Monotonicity of Limits\n and Sandwich Theorem",
                        "meta": " RA05 ",
                        "content": "Taking limits respects weak inequalities and sandwiching a sequence by two converging sequences reveals its limit. The technique of sandwiching can be used to determine limits via nested intervals.",
                        "notes": "104-snippet.html",
                        "video": "",
                        "webwork": "https://jupyterhub.mat.tu-harburg.de/webwork2/html2xml?&answersSubmitted=0&sourceFilePath=Library/Hope/Calc2/APEX_08_01_Sequences/Q_17.pg&problemSeed=123567890&displayMode=MathJax&courseID=pontifex&userID=pontifexuser&course_password=ki(JH7j3m4)k_46)&outputformat=simple",
                        "podcast": "",
                        "youtube": "https://youtu.be/Y6rRSip3QN4?start=14",
                        "spotify": "",
                        "color": "#b8b8b8"
                  }
            },
            {
                  "data": {
                        "id": "115",
                        "label": "Cauchy\nSequences",
                        "meta": " RA07 ",
                        "content": "The sequence members of a Cauchy Sequence eventually become arbitrarily close to each other.",
                        "notes": "115-snippet.html",
                        "video": "",
                        "exercise": "ratest07.html",
                        "podcast": "<p>Courtesy of Marcus Waurick. <i>Well-defined & Wonderful podcast</i>, <a href=\"https://www.marcus-waurick.de/teaching\" target=\"_blank\">marcus-waurick.de</a>.</p>",
                        "youtube": "https://youtu.be/R2AFZD0jiKQ?start=14",
                        "spotify": "https://open.spotify.com/embed/episode/2oh22JbFBcqSdfBJHEYUGo",
                        "color": "#b8b8b8"
                  }
            },
            {
                  "data": {
                        "id": "110",
                        "label": "Open, Closed,\nCompact Sets",
                        "meta": " RA13 ",
                        "content": "Important notions for subsets of real numbers.",
                        "notes": "110-snippet.html",
                        "video": "",
                        "exercise": "ratest13.html",
                        "podcast": "",
                        "youtube": "https://youtu.be/Wqo4Svs4erw?start=12",
                        "spotify": "",
                        "color": "#b8b8b8"
                  }
            },
            {
                  "data": {
                        "id": "107",
                        "label": "Subsequences and\nAccumulation Values",
                        "meta": " RA09 ",
                        "content": "A sequence that does not converge may still have converging subsequences.",
                        "notes": "107-snippet.html",
                        "video": "",
                        "exercise": "ratest09.html",
                        "podcast": "",
                        "youtube": "https://youtu.be/xZ5vjdZzTUI?start=14",
                        "spotify": "",
                        "color": "#b8b8b8"
                  }
            },
            {
                  "data": {
                        "id": "108",
                        "label": "Bolzano-Weierstrass\nTheorem",
                        "meta": "RA10 ",
                        "content": "Every bounded sequence has at least one converging subsequence.",
                        "notes": "108-snippet.html",
                        "video": "",
                        "exercise": "ratest10.html",
                        "podcast": "<p>Courtesy of Marcus Waurick. <i>Well-defined & Wonderful podcast</i>, <a href=\"https://www.marcus-waurick.de/teaching\" target=\"_blank\">marcus-waurick.de</a>.</p>",
                        "youtube": "https://youtu.be/e2QaNklYZGg?start=10",
                        "spotify": "https://open.spotify.com/embed/episode/4MKVAhO2q57xmMn1P7ONKg",
                        "color": "#b8b8b8"
                  }
            },
            {
                  "data": {
                        "id": "200",
                        "label": "Series and\nPartial Sums",
                        "meta": "RA15",
                        "content": "A series is a sequence of partial sums.",
                        "notes": "200-snippet.html",
                        "video": "",
                        "webwork": "https://jupyterhub.mat.tu-harburg.de/webwork2/html2xml?&answersSubmitted=0&sourceFilePath=Library/WHFreeman/Rogawski_Calculus_Early_Transcendentals_Second_Edition/10_Infinite_Series/10.2_Summing_an_Infinite_Series/10.2.3.pg&problemSeed=123567890&displayMode=MathJax&courseID=pontifex&userID=pontifexuser&course_password=ki(JH7j3m4)k_46)&outputformat=simple",
                        "podcast": "<p>Courtesy of Marcus Waurick. <i>Well-defined & Wonderful podcast</i>, <a href=\"https://www.marcus-waurick.de/teaching\" target=\"_blank\">marcus-waurick.de</a>.</p>",
                        "youtube": "https://youtu.be/BgfP3riDcrc?start=13",
                        "spotify": "https://open.spotify.com/embed/episode/4rf4zO7V8UJErJxgzmZFgh",
                        "color": "#b8b8b8"
                  }
            },
            {
                  "data": {
                        "id": "303",
                        "label": "Limits of Functions",
                        "meta": "RA26",
                        "content": "How function evaluations change when the argument approaches a certain point.",
                        "notes": "303-snippet.html",
                        "video": "",
                        "webwork": "https://jupyterhub.mat.tu-harburg.de/webwork2/html2xml?&answersSubmitted=0&sourceFilePath=Library/ASU-topics/setRateChange/3-2-72.pg&problemSeed=123567890&displayMode=MathJax&courseID=pontifex&userID=pontifexuser&course_password=ki(JH7j3m4)k_46)&outputformat=simple",
                        "podcast": "",
                        "youtube": "https://youtu.be/QoLlvvro6rE?start=15",
                        "spotify": "",
                        "color": "#b8b8b8"
                  }
            },
            {
                  "data": {
                        "id": "304",
                        "label": "Continuity",
                        "meta": "RA27",
                        "content": "The concept that relates functions with convergent sequences.",
                        "notes": "304-snippet.html",
                        "video": "",
                        "webwork": "https://jupyterhub.mat.tu-harburg.de/webwork2/html2xml?&answersSubmitted=0&sourceFilePath=Library/ASU-topics/setContinuity/4-1-57.pg&problemSeed=123567890&displayMode=MathJax&courseID=pontifex&userID=pontifexuser&course_password=ki(JH7j3m4)k_46)&outputformat=simple",
                        "podcast": "",
                        "youtube": "https://youtu.be/8VTG6EsyJh4?start=8",
                        "spotify": "",
                        "color": "#b8b8b8"
                  }
            },
            {
                  "data": {
                        "id": "114",
                        "label": "Bounded Monotonic\nSequences",
                        "meta": " ",
                        "content": "If a sequence of real numbers is bounded and monotonic, then it is convergent.",
                        "notes": "114-snippet.html",
                        "video": "",
                        "webwork": "https://jupyterhub.mat.tu-harburg.de/webwork2/html2xml?&answersSubmitted=0&sourceFilePath=Library/WinonaState/StewartCalcEarlyTran7ed/Chap11Section01/SCalcET7-11-1-027.pg&problemSeed=123567890&displayMode=MathJax&courseID=pontifex&userID=pontifexuser&course_password=ki(JH7j3m4)k_46)&outputformat=simple",
                        "podcast": "",
                        "youtube": "https://youtu.be/R2AFZD0jiKQ?start=450",
                        "spotify": "",
                        "color": "#b8b8b8"
                  }
            },
            {
                  "data": {
                        "id": "000",
                        "label": "Logical Statements\nand Operations",
                        "meta": " SLL01",
                        "content": "Logic is the foundation to formulate proofs and to understand the language of mathematics.",
                        "notes": "000-snippet.html",
                        "video": "",
                        "webwork": "https://jupyterhub.mat.tu-harburg.de/webwork2/html2xml?&answersSubmitted=0&sourceFilePath=Library/SDSU/Discrete/Logic/ttcontratautB4.pg&problemSeed=123567890&displayMode=MathJax&courseID=pontifex&userID=pontifexuser&course_password=ki(JH7j3m4)k_46)&outputformat=simple",
                        "podcast": "",
                        "youtube": "https://youtu.be/DU4wKBDm2Z4?start=9",
                        "spotify": "",
                        "color": "#abe8ef"
                  }
            },
            {
                  "data": {
                        "id": "002",
                        "label": "Real Numbers",
                        "meta": " SLR03  ",
                        "content": "In a real analysis, the real numbers are the largest number set we need. They satisfy axioms that represent the idea of a number line.",
                        "notes": "002-snippet.html",
                        "video": "",
                        "webwork": "https://jupyterhub.mat.tu-harburg.de/webwork2/html2xml?&answersSubmitted=0&sourceFilePath=Library/Mizzou/Intermediate_Algebra/Compound_Inequalities/P_02.pg&problemSeed=123567890&displayMode=MathJax&courseID=pontifex&userID=pontifexuser&course_password=ki(JH7j3m4)k_46)&outputformat=simple",
                        "podcast": "<p>Courtesy of Marcus Waurick. <i>Well-defined & Wonderful podcast</i>, <a href=\"https://www.marcus-waurick.de/teaching\" target=\"_blank\">marcus-waurick.de</a>.</p>",
                        "youtube": "https://youtu.be/E2MAvASTcg4?start=19",
                        "spotify": "https://open.spotify.com/embed/episode/1i62R3ZdwhjASp1TNJ2Bcy",
                        "color": "#abe8ef"
                  }
            },
            {
                  "data": {
                        "id": "100",
                        "label": "Sequences",
                        "meta": " RA02 ",
                        "content": "These object are needed to define limits later on.",
                        "notes": "100-snippet.html",
                        "video": "",
                        "webwork": "https://jupyterhub.mat.tu-harburg.de/webwork2/html2xml?&answersSubmitted=0&sourceFilePath=Library/UMN/calculusStewartCCC/s_11_1_5.pg&problemSeed=123567890&displayMode=MathJax&courseID=pontifex&userID=pontifexuser&course_password=ki(JH7j3m4)k_46)&outputformat=simple",
                        "podcast": "",
                        "youtube": "https://youtu.be/1SguKALJji8?start=17",
                        "spotify": "",
                        "color": "#abe8ef"
                  }
            }
      ],
      "edges": [
            {
                  "data": {
                        "source": "101",
                        "target": "102",
                        "label": "Convergent sequences are bounded but not every bounded sequence is convergent.",
                        "color": "#b8b8b8",
                        "style": "dashed"
                  }
            },
            {
                  "data": {
                        "source": "101",
                        "target": "109",
                        "label": "Limit inferior and limit superior are in particular limits.",
                        "color": "#b8b8b8",
                        "style": "dashed"
                  }
            },
            {
                  "data": {
                        "source": "101",
                        "target": "103",
                        "label": "Calculating limits of sums, products or quotients of convergent sequences.",
                        "color": "#b8b8b8",
                        "style": "dashed"
                  }
            },
            {
                  "data": {
                        "source": "101",
                        "target": "104",
                        "label": "Monotonicity and boundedness imply convergence.",
                        "color": "#b8b8b8",
                        "style": "dashed"
                  }
            },
            {
                  "data": {
                        "source": "101",
                        "target": "115",
                        "label": "Every convergent sequence is also a Cauchy sequence.",
                        "color": "#b8b8b8",
                        "style": "dashed"
                  }
            },
            {
                  "data": {
                        "source": "101",
                        "target": "110",
                        "label": "Closedness is characterised by convergence of sequences.",
                        "color": "#b8b8b8",
                        "style": "dashed"
                  }
            },
            {
                  "data": {
                        "source": "101",
                        "target": "107",
                        "label": "A sequence may have a convergent subsequence and this limit is then an accumulation value of the original sequence.",
                        "color": "#b8b8b8",
                        "style": "dashed"
                  }
            },
            {
                  "data": {
                        "source": "101",
                        "target": "108",
                        "label": "The Bolzano-Weierstrass theorem guarantees convergence of certain sequences.",
                        "color": "#b8b8b8",
                        "style": "dashed"
                  }
            },
            {
                  "data": {
                        "source": "101",
                        "target": "200",
                        "label": "A convergent series is a convergent sequence of partial sums.",
                        "color": "#b8b8b8",
                        "style": "dashed"
                  }
            },
            {
                  "data": {
                        "source": "101",
                        "target": "303",
                        "label": "Limits of functions are limits of sequences of real numbers.",
                        "color": "#b8b8b8",
                        "style": "dashed"
                  }
            },
            {
                  "data": {
                        "source": "101",
                        "target": "304",
                        "label": "Continuous functions map convergent sequences to convergent sequences.",
                        "color": "#b8b8b8",
                        "style": "dashed"
                  }
            },
            {
                  "data": {
                        "source": "101",
                        "target": "114",
                        "label": "If a sequence is bounded and monotonic, then it converges.",
                        "color": "#b8b8b8",
                        "style": "dashed"
                  }
            },
            {
                  "data": {
                        "source": "000",
                        "target": "101",
                        "label": "The definition of convergence is one of the very first logical statements that involves quantifiers.",
                        "color": "#abe8ef",
                        "style": "solid"
                  }
            },
            {
                  "data": {
                        "source": "002",
                        "target": "101",
                        "label": "The definition of convergence involves the absolute value of a difference of real numbers and a quantitative comparison with another real number.",
                        "color": "#abe8ef",
                        "style": "solid"
                  }
            },
            {
                  "data": {
                        "source": "100",
                        "target": "101",
                        "label": "Having a limit is a property of a sequence.",
                        "color": "#abe8ef",
                        "style": "solid"
                  }
            }
      ]
}
